demurr/__init__.py
demurr/__init__.pyi
demurr/_msvc_module.pyi
demurr/_msvc_module.pypy310-pp73-win_amd64.pyd
demurr/_msvc_module_d.pdb
demurr/_msvc_module_d.pyi
demurr/_msvc_module_d.pypy310-pp73-win_amd64.pyd
demurr/msvc.py
demurr/msvc.pyi
demurr/py.typed
demurr-0.0.1.dist-info/METADATA
demurr-0.0.1.dist-info/WHEEL
demurr-0.0.1.dist-info/entry_points.txt
demurr-0.0.1.dist-info/RECORD
